PVWatts_Tool/PVWatts_API.py
PVWatts_Tool/__init__.py
PVWatts_Tool/__main__.py
PVWatts_Tool/dataframe_template.py
PVWatts_Tool/nrel_requests.py
PVWatts_Tool/process_output.py
PVWatts_Tool-1.0.3.dist-info/DESCRIPTION.rst
PVWatts_Tool-1.0.3.dist-info/METADATA
PVWatts_Tool-1.0.3.dist-info/RECORD
PVWatts_Tool-1.0.3.dist-info/WHEEL
PVWatts_Tool-1.0.3.dist-info/metadata.json
PVWatts_Tool-1.0.3.dist-info/top_level.txt
